cs_binding_generator/__init__.py
cs_binding_generator/_version.py
cs_binding_generator/code_generators.py
cs_binding_generator/config.py
cs_binding_generator/constants.py
cs_binding_generator/generator.py
cs_binding_generator/main.py
cs_binding_generator/type_mapper.py
cs_binding_generator-1.0.1.dev22.dist-info/licenses/LICENSE
cs_binding_generator-1.0.1.dev22.dist-info/METADATA
cs_binding_generator-1.0.1.dev22.dist-info/WHEEL
cs_binding_generator-1.0.1.dev22.dist-info/entry_points.txt
cs_binding_generator-1.0.1.dev22.dist-info/top_level.txt
cs_binding_generator-1.0.1.dev22.dist-info/RECORD
