Metadata-Version: 2.4
Name: cs_binding_generator
Version: 1.0.1.dev22
Summary: Generate C# bindings from C headers using libclang with modern LibraryImport
Author-email: Robin 'Ruadeil' Degen <mail@ruadeil.lgbt>
License-Expression: MIT
Project-URL: Homepage, https://github.com/cs-binding-generator/cs-binding-generator
Project-URL: Repository, https://github.com/cs-binding-generator/cs-binding-generator
Project-URL: Issues, https://github.com/cs-binding-generator/cs-binding-generator
Keywords: csharp,bindings,interop,libclang,code-generation
Classifier: Development Status :: 3 - Alpha
Classifier: Intended Audience :: Developers
Classifier: Programming Language :: Python :: 3
Classifier: Programming Language :: Python :: 3.12
Classifier: Programming Language :: Python :: 3.13
Classifier: Programming Language :: C
Classifier: Programming Language :: C#
Classifier: Topic :: Software Development :: Code Generators
Classifier: Topic :: Software Development :: Libraries
Requires-Python: >=3.12
License-File: LICENSE
Requires-Dist: libclang>=16.0.0
Provides-Extra: dev
Requires-Dist: pytest>=7.0; extra == "dev"
Requires-Dist: black>=23.0; extra == "dev"
Requires-Dist: mypy>=1.0; extra == "dev"
Dynamic: license-file
